README.rst
setup.py
aptly/__init__.py
aptly/client.py
aptly/decorators.py
aptly/exceptions.py
aptly/publisher/__init__.py
aptly/publisher/__main__.py
python_aptly.egg-info/PKG-INFO
python_aptly.egg-info/SOURCES.txt
python_aptly.egg-info/dependency_links.txt
python_aptly.egg-info/entry_points.txt
python_aptly.egg-info/requires.txt
python_aptly.egg-info/top_level.txt