Metadata-Version: 1.1
Name: python-aptly
Version: 0.12.12
Summary: Aptly REST API client and tooling
Home-page: https://github.com/tcpcloud/python-aptly
Author: Filip Pytloun
Author-email: filip.pytloun@tcpcloud.eu
License: GPLv2
Keywords: aptly debian repository
Platform: UNKNOWN
Classifier: Development Status :: 4 - Beta
Classifier: Environment :: Console
Classifier: Intended Audience :: System Administrators
Classifier: License :: OSI Approved :: GNU General Public License v2 (GPLv2)
Classifier: Operating System :: OS Independent
Classifier: Programming Language :: Python
Classifier: Programming Language :: Python :: 2
Classifier: Programming Language :: Python :: 2.7
Classifier: Programming Language :: Python :: 3
